{
  "schemaVersion": "1.0",
  "country": "BJ",
  "countryName": "Bénin",
  "countryNames": {
    "fr": "Bénin",
    "en": "Benin"
  },
  "timezone": "Africa/Porto-Novo",
  "year": 2026,
  "month": 3,
  "workingDaysCount": 21,
  "weekendDaysCount": 9,
  "publicHolidaysCount": 1,
  "days": [
    {
      "date": "2026-03-01",
      "dayOfWeek": 7,
      "isWeekend": true,
      "isPublicHoliday": false,
      "isWorkingDay": false,
      "isFirstWorkingDayOfMonth": false,
      "isLastWorkingDayOfMonth": false,
      "isRamadanPeriod": false,
      "confidence": "confirmed"
    },
    {
      "date": "2026-03-02",
      "dayOfWeek": 1,
      "isWeekend": false,
      "isPublicHoliday": false,
      "isWorkingDay": true,
      "isFirstWorkingDayOfMonth": true,
      "isLastWorkingDayOfMonth": false,
      "isRamadanPeriod": false,
      "confidence": "confirmed"
    },
    {
      "date": "2026-03-03",
      "dayOfWeek": 2,
      "isWeekend": false,
      "isPublicHoliday": false,
      "isWorkingDay": true,
      "isFirstWorkingDayOfMonth": false,
      "isLastWorkingDayOfMonth": false,
      "isRamadanPeriod": false,
      "confidence": "confirmed"
    },
    {
      "date": "2026-03-04",
      "dayOfWeek": 3,
      "isWeekend": false,
      "isPublicHoliday": false,
      "isWorkingDay": true,
      "isFirstWorkingDayOfMonth": false,
      "isLastWorkingDayOfMonth": false,
      "isRamadanPeriod": false,
      "confidence": "confirmed"
    },
    {
      "date": "2026-03-05",
      "dayOfWeek": 4,
      "isWeekend": false,
      "isPublicHoliday": false,
      "isWorkingDay": true,
      "isFirstWorkingDayOfMonth": false,
      "isLastWorkingDayOfMonth": false,
      "isRamadanPeriod": false,
      "confidence": "confirmed"
    },
    {
      "date": "2026-03-06",
      "dayOfWeek": 5,
      "isWeekend": false,
      "isPublicHoliday": false,
      "isWorkingDay": true,
      "isFirstWorkingDayOfMonth": false,
      "isLastWorkingDayOfMonth": false,
      "isRamadanPeriod": false,
      "confidence": "confirmed"
    },
    {
      "date": "2026-03-07",
      "dayOfWeek": 6,
      "isWeekend": true,
      "isPublicHoliday": false,
      "isWorkingDay": false,
      "isFirstWorkingDayOfMonth": false,
      "isLastWorkingDayOfMonth": false,
      "isRamadanPeriod": false,
      "confidence": "confirmed"
    },
    {
      "date": "2026-03-08",
      "dayOfWeek": 7,
      "isWeekend": true,
      "isPublicHoliday": false,
      "isWorkingDay": false,
      "isFirstWorkingDayOfMonth": false,
      "isLastWorkingDayOfMonth": false,
      "isRamadanPeriod": false,
      "confidence": "confirmed"
    },
    {
      "date": "2026-03-09",
      "dayOfWeek": 1,
      "isWeekend": false,
      "isPublicHoliday": false,
      "isWorkingDay": true,
      "isFirstWorkingDayOfMonth": false,
      "isLastWorkingDayOfMonth": false,
      "isRamadanPeriod": false,
      "confidence": "confirmed"
    },
    {
      "date": "2026-03-10",
      "dayOfWeek": 2,
      "isWeekend": false,
      "isPublicHoliday": false,
      "isWorkingDay": true,
      "isFirstWorkingDayOfMonth": false,
      "isLastWorkingDayOfMonth": false,
      "isRamadanPeriod": false,
      "confidence": "confirmed"
    },
    {
      "date": "2026-03-11",
      "dayOfWeek": 3,
      "isWeekend": false,
      "isPublicHoliday": false,
      "isWorkingDay": true,
      "isFirstWorkingDayOfMonth": false,
      "isLastWorkingDayOfMonth": false,
      "isRamadanPeriod": false,
      "confidence": "confirmed"
    },
    {
      "date": "2026-03-12",
      "dayOfWeek": 4,
      "isWeekend": false,
      "isPublicHoliday": false,
      "isWorkingDay": true,
      "isFirstWorkingDayOfMonth": false,
      "isLastWorkingDayOfMonth": false,
      "isRamadanPeriod": false,
      "confidence": "confirmed"
    },
    {
      "date": "2026-03-13",
      "dayOfWeek": 5,
      "isWeekend": false,
      "isPublicHoliday": false,
      "isWorkingDay": true,
      "isFirstWorkingDayOfMonth": false,
      "isLastWorkingDayOfMonth": false,
      "isRamadanPeriod": false,
      "confidence": "confirmed"
    },
    {
      "date": "2026-03-14",
      "dayOfWeek": 6,
      "isWeekend": true,
      "isPublicHoliday": false,
      "isWorkingDay": false,
      "isFirstWorkingDayOfMonth": false,
      "isLastWorkingDayOfMonth": false,
      "isRamadanPeriod": false,
      "confidence": "confirmed"
    },
    {
      "date": "2026-03-15",
      "dayOfWeek": 7,
      "isWeekend": true,
      "isPublicHoliday": false,
      "isWorkingDay": false,
      "isFirstWorkingDayOfMonth": false,
      "isLastWorkingDayOfMonth": false,
      "isRamadanPeriod": false,
      "confidence": "confirmed"
    },
    {
      "date": "2026-03-16",
      "dayOfWeek": 1,
      "isWeekend": false,
      "isPublicHoliday": false,
      "isWorkingDay": true,
      "isFirstWorkingDayOfMonth": false,
      "isLastWorkingDayOfMonth": false,
      "isRamadanPeriod": false,
      "confidence": "confirmed"
    },
    {
      "date": "2026-03-17",
      "dayOfWeek": 2,
      "isWeekend": false,
      "isPublicHoliday": false,
      "isWorkingDay": true,
      "isFirstWorkingDayOfMonth": false,
      "isLastWorkingDayOfMonth": false,
      "isRamadanPeriod": false,
      "confidence": "confirmed"
    },
    {
      "date": "2026-03-18",
      "dayOfWeek": 3,
      "isWeekend": false,
      "isPublicHoliday": false,
      "isWorkingDay": true,
      "isFirstWorkingDayOfMonth": false,
      "isLastWorkingDayOfMonth": false,
      "isRamadanPeriod": false,
      "confidence": "confirmed"
    },
    {
      "date": "2026-03-19",
      "dayOfWeek": 4,
      "isWeekend": false,
      "isPublicHoliday": false,
      "isWorkingDay": true,
      "isFirstWorkingDayOfMonth": false,
      "isLastWorkingDayOfMonth": false,
      "isRamadanPeriod": false,
      "confidence": "confirmed"
    },
    {
      "date": "2026-03-20",
      "dayOfWeek": 5,
      "isWeekend": false,
      "isPublicHoliday": true,
      "isWorkingDay": false,
      "isFirstWorkingDayOfMonth": false,
      "isLastWorkingDayOfMonth": false,
      "isRamadanPeriod": false,
      "confidence": "tentative"
    },
    {
      "date": "2026-03-21",
      "dayOfWeek": 6,
      "isWeekend": true,
      "isPublicHoliday": false,
      "isWorkingDay": false,
      "isFirstWorkingDayOfMonth": false,
      "isLastWorkingDayOfMonth": false,
      "isRamadanPeriod": false,
      "confidence": "confirmed"
    },
    {
      "date": "2026-03-22",
      "dayOfWeek": 7,
      "isWeekend": true,
      "isPublicHoliday": false,
      "isWorkingDay": false,
      "isFirstWorkingDayOfMonth": false,
      "isLastWorkingDayOfMonth": false,
      "isRamadanPeriod": false,
      "confidence": "confirmed"
    },
    {
      "date": "2026-03-23",
      "dayOfWeek": 1,
      "isWeekend": false,
      "isPublicHoliday": false,
      "isWorkingDay": true,
      "isFirstWorkingDayOfMonth": false,
      "isLastWorkingDayOfMonth": false,
      "isRamadanPeriod": false,
      "confidence": "confirmed"
    },
    {
      "date": "2026-03-24",
      "dayOfWeek": 2,
      "isWeekend": false,
      "isPublicHoliday": false,
      "isWorkingDay": true,
      "isFirstWorkingDayOfMonth": false,
      "isLastWorkingDayOfMonth": false,
      "isRamadanPeriod": false,
      "confidence": "confirmed"
    },
    {
      "date": "2026-03-25",
      "dayOfWeek": 3,
      "isWeekend": false,
      "isPublicHoliday": false,
      "isWorkingDay": true,
      "isFirstWorkingDayOfMonth": false,
      "isLastWorkingDayOfMonth": false,
      "isRamadanPeriod": false,
      "confidence": "confirmed"
    },
    {
      "date": "2026-03-26",
      "dayOfWeek": 4,
      "isWeekend": false,
      "isPublicHoliday": false,
      "isWorkingDay": true,
      "isFirstWorkingDayOfMonth": false,
      "isLastWorkingDayOfMonth": false,
      "isRamadanPeriod": false,
      "confidence": "confirmed"
    },
    {
      "date": "2026-03-27",
      "dayOfWeek": 5,
      "isWeekend": false,
      "isPublicHoliday": false,
      "isWorkingDay": true,
      "isFirstWorkingDayOfMonth": false,
      "isLastWorkingDayOfMonth": false,
      "isRamadanPeriod": false,
      "confidence": "confirmed"
    },
    {
      "date": "2026-03-28",
      "dayOfWeek": 6,
      "isWeekend": true,
      "isPublicHoliday": false,
      "isWorkingDay": false,
      "isFirstWorkingDayOfMonth": false,
      "isLastWorkingDayOfMonth": false,
      "isRamadanPeriod": false,
      "confidence": "confirmed"
    },
    {
      "date": "2026-03-29",
      "dayOfWeek": 7,
      "isWeekend": true,
      "isPublicHoliday": false,
      "isWorkingDay": false,
      "isFirstWorkingDayOfMonth": false,
      "isLastWorkingDayOfMonth": false,
      "isRamadanPeriod": false,
      "confidence": "confirmed"
    },
    {
      "date": "2026-03-30",
      "dayOfWeek": 1,
      "isWeekend": false,
      "isPublicHoliday": false,
      "isWorkingDay": true,
      "isFirstWorkingDayOfMonth": false,
      "isLastWorkingDayOfMonth": false,
      "isRamadanPeriod": false,
      "confidence": "confirmed"
    },
    {
      "date": "2026-03-31",
      "dayOfWeek": 2,
      "isWeekend": false,
      "isPublicHoliday": false,
      "isWorkingDay": true,
      "isFirstWorkingDayOfMonth": false,
      "isLastWorkingDayOfMonth": true,
      "isRamadanPeriod": false,
      "confidence": "confirmed"
    }
  ]
}